{
  "title": "Casa MM",
  "year": "2024",
  "location": "Kaunas, Lituania",
  "type": [
    "Exterior",
    "Construcție nouă",
    "Rezidențial"
  ],
  "shortDescription": "O reședință cu două etaje, unde forma geometrică strictă se întâlnește cu un cadru natural. Compoziția clădirii este formată din două volume clar distincte - un cub superior monumental, întunecat, și un parter mai deschis, placat cu lemn, care pare să se dizolve în peisaj. Ideea centrală a proiectului este un portal circular în fațadă, care servește drept prag simbolic între domeniul public și cel privat. Acest motiv aduce un sentiment de jucăușenie și poezie unei clădiri altfel ascetice.",
  "images": [
    "/uploads/projects/3/Main.jpg",
    "/uploads/projects/3/2.jpg",
    "/uploads/projects/3/3.jpg",
    "/uploads/projects/3/4.jpg",
    "/uploads/projects/3/5.jpg"
  ],
  "featured": true,
  "order": 3
}